{
    "key": "group_55cdf66998fd9",
    "title": "Site Calls to Action",
    "fields": [
        {
            "key": "field_560431a4fb6a2",
            "label": "Link",
            "name": "",
            "type": "tab",
            "instructions": "",
            "required": 0,
            "conditional_logic": 0,
            "wrapper": {
                "width": "",
                "class": "",
                "id": ""
            },
            "placement": "left",
            "endpoint": 0
        },
        {
            "key": "field_57c61faa79d1b",
            "label": "CTA Link",
            "name": "cta_link",
            "type": "clone",
            "value": null,
            "instructions": "",
            "required": 0,
            "conditional_logic": 0,
            "wrapper": {
                "width": "",
                "class": "",
                "id": ""
            },
            "clone": [
                "group_57c61ddfac29f"
            ],
            "prefix_label": 0,
            "prefix_name": 0,
            "display": "seamless",
            "layout": "block"
        },
        {
            "key": "field_58811d23f0476",
            "label": "Callout Text",
            "name": "cta_callout_text",
            "type": "text",
            "value": null,
            "instructions": "",
            "required": 0,
            "conditional_logic": 0,
            "wrapper": {
                "width": "",
                "class": "",
                "id": ""
            },
            "default_value": "",
            "maxlength": "",
            "placeholder": "optional",
            "prepend": "",
            "append": ""
        }
    ],
    "location": [
        [
            {
                "param": "post_type",
                "operator": "==",
                "value": "post"
            }
        ]
    ],
    "menu_order": 0,
    "position": "normal",
    "style": "default",
    "label_placement": "top",
    "instruction_placement": "label",
    "hide_on_screen": [
        "permalink",
        "the_content",
        "excerpt",
        "custom_fields",
        "discussion",
        "comments",
        "revisions",
        "slug",
        "author",
        "format",
        "featured_image",
        "categories",
        "tags",
        "send-trackbacks"
    ],
    "active": 0,
    "description": "",
    "modified": 1508442856
}